dissectica/__init__.py
dissectica/dissectica.py
dissectica_cdp_client-0.1.1.dist-info/licenses/LICENSE
dissectica_cdp_client-0.1.1.dist-info/METADATA
dissectica_cdp_client-0.1.1.dist-info/WHEEL
dissectica_cdp_client-0.1.1.dist-info/top_level.txt
dissectica_cdp_client-0.1.1.dist-info/RECORD
