Metadata-Version: 2.4
Name: dissectica-cdp-client
Version: 0.1.1
Summary: The official Python SDK for the Dissectica Customer Data Platform.
Author-email: sathyasubrahmanya v s <sathyasubrahmanya@webcastle.in>
License: MIT License
Project-URL: Homepage, https://gitlab.com/sathyasubrahmanya/dissectica-client-python
Project-URL: Bug Tracker, https://gitlab.com/sathyasubrahmanya/dissectica-client-python/-/issues
Classifier: Programming Language :: Python :: 3
Classifier: License :: OSI Approved :: MIT License
Classifier: Operating System :: OS Independent
Classifier: Development Status :: 4 - Beta
Classifier: Intended Audience :: Developers
Classifier: Topic :: Software Development :: Libraries :: Python Modules
Classifier: Topic :: System :: Logging
Requires-Python: >=3.12
License-File: LICENSE
Requires-Dist: requests
Requires-Dist: avro-python3
Dynamic: license-file
